odoo/addons/website_whatsapp/README.rst
odoo/addons/website_whatsapp/__init__.py
odoo/addons/website_whatsapp/__manifest__.py
odoo/addons/website_whatsapp/i18n/es.po
odoo/addons/website_whatsapp/i18n/it.po
odoo/addons/website_whatsapp/i18n/website_whatsapp.pot
odoo/addons/website_whatsapp/models/__init__.py
odoo/addons/website_whatsapp/models/res_config_settings.py
odoo/addons/website_whatsapp/models/website.py
odoo/addons/website_whatsapp/readme/CONFIGURE.md
odoo/addons/website_whatsapp/readme/CONTRIBUTORS.md
odoo/addons/website_whatsapp/readme/DESCRIPTION.md
odoo/addons/website_whatsapp/static/description/icon.png
odoo/addons/website_whatsapp/static/description/index.html
odoo/addons/website_whatsapp/static/src/scss/website.scss
odoo/addons/website_whatsapp/templates/website.xml
odoo/addons/website_whatsapp/tests/__init__.py
odoo/addons/website_whatsapp/tests/test_res_config_settings.py
odoo/addons/website_whatsapp/views/res_config_settings.xml
odoo_addon_website_whatsapp-18.0.1.0.1.dist-info/METADATA
odoo_addon_website_whatsapp-18.0.1.0.1.dist-info/WHEEL
odoo_addon_website_whatsapp-18.0.1.0.1.dist-info/top_level.txt
odoo_addon_website_whatsapp-18.0.1.0.1.dist-info/RECORD
