Metadata-Version: 2.1
Name: odoo-addon-website_whatsapp
Version: 18.0.1.0.1
Requires-Python: >=3.10
Requires-Dist: odoo==18.0.*
Summary: Whatsapp integration
Home-page: https://github.com/OCA/website
License: AGPL-3
Author: Studio73, Odoo Community Association (OCA)
Author-email: support@odoo-community.org
Classifier: Programming Language :: Python
Classifier: Framework :: Odoo
Classifier: Framework :: Odoo :: 18.0
Classifier: License :: OSI Approved :: GNU Affero General Public License v3
